horkos/__init__.py
horkos/_cataloger.py
horkos/_fields.py
horkos/_schemaomatic.py
horkos/_yaml_parser.py
horkos/checks.py
horkos/errors.py
horkos/inspector.py
horkos/types.py
horkos/cmdline/__init__.py
horkos/cmdline/check.py
horkos/cmdline/critique.py
horkos/critiquer/__init__.py
horkos/critiquer/_casing.py
horkos/critiquer/_definitions.py
horkos/critiquer/_typing.py
horkos/critiquer/_utils.py
tests/__init__.py
tests/test_cataloger.py
tests/test_checks.py
tests/test_cmdline.py
tests/test_cmdline_check.py
tests/test_cmdline_critique.py
tests/test_critiquer_casing.py
tests/test_critiquer_typing.py
tests/test_schemaomatic.py
tests/test_types.py
tests/test_yaml_parser.py
horkos-0.2.7.dist-info/METADATA
horkos-0.2.7.dist-info/WHEEL
horkos-0.2.7.dist-info/entry_points.txt
horkos-0.2.7.dist-info/top_level.txt
horkos-0.2.7.dist-info/RECORD
