Metadata-Version: 2.1
Name: horkos
Version: 0.2.7
Summary: A library for validating data at the edges of data systems.
Home-page: https://gitlab.com/kjschiroo/horkos
Author: Kevin Schiroo
Author-email: kjschiroo@gmail.com
License: MIT
Project-URL: Documentation, https://horkos.readthedocs.io/
Project-URL: Code, https://gitlab.com/kjschiroo/horkos
Project-URL: Issues, https://gitlab.com/kjschiroo/horkos/-/issues
Platform: UNKNOWN
Classifier: Programming Language :: Python :: 3
Classifier: License :: OSI Approved :: MIT License
Requires-Python: >=3.7
Requires-Dist: pyyaml
